pipecat_ai_whisker-0.0.11.dist-info/licenses/LICENSE
pipecat_whisker/__init__.py
pipecat_whisker/frames.py
pipecat_whisker/observer.py
pipecat_whisker/py.typed
pipecat_ai_whisker-0.0.11.dist-info/METADATA
pipecat_ai_whisker-0.0.11.dist-info/WHEEL
pipecat_ai_whisker-0.0.11.dist-info/top_level.txt
pipecat_ai_whisker-0.0.11.dist-info/RECORD
