Metadata-Version: 2.4
Name: pipecat-ai-whisker
Version: 0.0.11
Summary: A real-time debugger for Pipecat
License-Expression: BSD-2-Clause
Project-URL: Source, https://github.com/pipecat-ai/whisker
Project-URL: Website, https://pipecat.ai
Keywords: pipecat,debug,ai
Classifier: Development Status :: 5 - Production/Stable
Classifier: Intended Audience :: Developers
Classifier: Topic :: Communications :: Conferencing
Classifier: Topic :: Multimedia :: Sound/Audio
Classifier: Topic :: Multimedia :: Video
Classifier: Topic :: Scientific/Engineering :: Artificial Intelligence
Requires-Python: >=3.10
License-File: LICENSE
Requires-Dist: aiofiles<25,>=24.1.0
Requires-Dist: loguru<1,>=0.7.3
Requires-Dist: msgpack<2,>=1.1.1
Requires-Dist: pipecat-ai>=0.0.81
Requires-Dist: websockets<15.0,>=13.1
Dynamic: license-file
